cleanPyData/__init__.py
cleanPyData/cleaning.py
cleanPyData/feature_extraction.py
cleanPyData/normalization.py
cleanPyData/outlier_detection.py
tests/__init__.py
tests/test_cleaning.py
tests/test_feature_extraction.py
tests/test_normalization.py
tests/test_outlier_detection.py
cleanPyData-0.1.8.dist-info/LICENSE
cleanPyData-0.1.8.dist-info/METADATA
cleanPyData-0.1.8.dist-info/WHEEL
cleanPyData-0.1.8.dist-info/top_level.txt
cleanPyData-0.1.8.dist-info/RECORD
