Metadata-Version: 2.1
Name: cleanPyData
Version: 0.1.8
Summary: A package for data cleaning and preprocessing
Home-page: https://github.com/Livingston-k/cleanPyData
Author: Kaddu Livingstone
Author-email: kaddulivingston@gmail.com
Classifier: Programming Language :: Python :: 3
Classifier: License :: OSI Approved :: MIT License
Classifier: Operating System :: OS Independent
Requires-Python: >=3.6
License-File: LICENSE
Requires-Dist: pandas >=1.0
Requires-Dist: scikit-learn >=0.24
